retroyaml/dictObj.py
retroyaml/yamlConf.py
retroyaml-0.0.1.dist-info/LICENSE
retroyaml-0.0.1.dist-info/METADATA
retroyaml-0.0.1.dist-info/WHEEL
retroyaml-0.0.1.dist-info/top_level.txt
retroyaml-0.0.1.dist-info/RECORD
