Metadata-Version: 2.1
Name: retroyaml
Version: 0.0.1
Home-page: https://github.com/retrontology/retroyaml
Author: retrontology
Author-email: retrontology@gmail.com
License: MIT
Keywords: yaml dict
License-File: LICENSE
Requires-Dist: pyyaml
